GPL-2.0
HISTORY
INSTALL
MANIFEST.in
README.md
_mysql.c
metadata.cfg
pymemcompat.h
setup.cfg
setup.py
setup_common.py
setup_posix.py
setup_windows.py
site.cfg
MySQL_python_embedded.egg-info/PKG-INFO
MySQL_python_embedded.egg-info/SOURCES.txt
MySQL_python_embedded.egg-info/dependency_links.txt
MySQL_python_embedded.egg-info/requires.txt
MySQL_python_embedded.egg-info/top_level.txt
MySQLdb_embedded/__init__.py
MySQLdb_embedded/connections.py
MySQLdb_embedded/converters.py
MySQLdb_embedded/cursors.py
MySQLdb_embedded/release.py
MySQLdb_embedded/times.py
MySQLdb_embedded/constants/CLIENT.py
MySQLdb_embedded/constants/CR.py
MySQLdb_embedded/constants/ER.py
MySQLdb_embedded/constants/FIELD_TYPE.py
MySQLdb_embedded/constants/FLAG.py
MySQLdb_embedded/constants/REFRESH.py
MySQLdb_embedded/constants/__init__.py
doc/FAQ.rst
doc/MySQLdb.constants.rst
doc/MySQLdb.rst
doc/_mysql.rst
doc/_mysql_exceptions.rst
doc/conf.py
doc/index.rst
doc/modules.rst
doc/user_guide.rst
tests/capabilities.py
tests/configdb.py
tests/dbapi20.py
tests/test_MySQLdb_capabilities.py
tests/test_MySQLdb_dbapi20.py
tests/test_MySQLdb_nonstandard.py